{
  "parameter": "Area Non Kritis Need to Check",
  "weeks": ["W12", "W13", "W14", "W15"],
  "sites": [
    "SMO",
    "PMO",
    "MARINE",
    "LMO",
    "HO",
    "GMO",
    "EKSPLORASI",
    "BMO 3",
    "BMO 2",
    "BMO 1"
  ],
  "bySite": {
    "SMO": { "W12": 11, "W13": 11, "W14": 11, "W15": 11 },
    "PMO": { "W12": 27, "W13": 27, "W14": 27, "W15": 27 },
    "MARINE": { "W12": 1, "W13": 1, "W14": 1, "W15": 1 },
    "LMO": { "W12": 15, "W13": 15, "W14": 15, "W15": 15 },
    "HO": { "W12": 5, "W13": 5, "W14": 5, "W15": 5 },
    "GMO": { "W12": 21, "W13": 21, "W14": 21, "W15": 21 },
    "EKSPLORASI": { "W12": 1, "W13": 1, "W14": 1, "W15": 1 },
    "BMO 3": { "W12": 1, "W13": 1, "W14": 1, "W15": 1 },
    "BMO 2": { "W12": 25, "W13": 25, "W14": 25, "W15": 25 },
    "BMO 1": { "W12": 22, "W13": 22, "W14": 22, "W15": 22 }
  }
}
